{
    "data": [
        {
            "page": 0,
            "text": "ецензии книго Петербурге\nО первых историках Петра Великого\nЗаметки на полях\nсовраменных изданий\nC. А. Мезин\nXVIII век в России прошел под\nзнаком петровских реформ. Уже со-\nвременники преобразований созна-\nвали значение событий, свидетеля-\nми которых они были, и стремились\nзапечатлеть их для потомков. Сам\nПетр I и его сподвижники - Фео-\nфан Прокопович, П. П. Шафиров,\nA. В. Макаров и др.- выступали в\nроли историков своего времени.\nБольшое значение придавалось\nсозданию официальной «Гистории\nСвейской войны». Однако русским\nсовременникам преобразователя\nтак и не удалось создать сколько-\nнибудь полную и завершенную\nисторию своего времени, которая\nчаще всего мыслилась как история\nПетра Великого.\nПервым, кто вознамерился опи-\nсать каждый день жизни Петра Ве-\nликого, был младший современник\nцаря «новгородский дворянин»\nП. Н. Крекшин (1684-1763). Его\nопыт написания истории Петра\nнельзя признать вполне удачным,\nно сам Крекшин представляет со-\nбой любопытное явление русской\nисториографии переходного периода.\nПрежде всего, он известен как автор\n«Краткого описания блаженных дел\nвеликого государя императора Петра\nВеликого»1, в котором жизнеописа-\nние царя доведено до 1706 года.\nГлавным делом своей жизни\nсам Крекшин считал составление\nподробных «Журналов» (общим\nчислом - 45, приблизительно по\nколичеству лет царствования),\nв\nкоторых он описывал каждый день\nжизни Петра I. Едва ли Крекшин\nзакончил работу над этими «Жур-\nналами»2. Во всяком случае до нас\nдошло лишь два тома - за 1683 и\n1709 годы.\n«Для скорейшего прочтения и\nудобнейшего вразумления» Крек-\nшин на основе своих «Журналов»\nсоставлял еще «Экстракты» (со-\nкращения), благодаря которым, по\nсловам автора, «всяк любопытству-\nющий читатель возможет без вели-\nкого утруждения великославные\nдела Петра Великого ведать». Впро-\nчем, экстракты краткостью тоже не\nотличаются. «Экстракт» журнала\nза 1682 год датирован 1754 годом3\nи представляет собой развернутую\nверсию событий, изложенных ранее\nв «Кратком описании». Менее изве-\nстен «Экстракт» журнала 1710 года\n(том 29), созданный Крекшиным в\n1758 году4.\nВ последнее время к сочинени-\nям П. Н. Крекшина отнесено еще\nодно, известное под названием «О\nзачатии и здании царствующаго\nграда Санктпетербурга». Оно не раз\nпривлекало внимание историков\nПетербурга, а в 1991 годубыло вновь\nопубликованоЮ.Н. Беспятых5. Еще\nс начала 1980-х годов мне приходи-\nлось работать с опубликованными и\nархивными текстами П. Н. Крекши-\nна. Внимательно познакомившись\nс публикацией Ю. Н. Беспятых,\nя не мог отделаться от ощущения\ndéjà-vu. Вновь оказавшись в РГАДА,\nя просмотрел «Краткое описание\nблаженных дел» и убедился, что\nпамять меня не подвела. В самом\nкрупном сочинении П. Н. Крек-\nшина повествование о жизни царя\n1703 года прерывается заголовком\n«О зачатии царствующего града\nСанкт-Петербурга», а далее следует\nзнакомый текст6, имеющий, правда,\nряд особенностей, свидетельствую-\nщих о разных стадиях авторской\nработы. Авторство П. Н. Крекшина\nв отношении сочинения «О зача-\nтии и здании царствующаго града\nСанктпетербурга» было обосновано\nмною в диссертации 1999 года7, по-\nсвященной русской и французской\nлитературе XVIII века о Петре I. Но\nтолько в 2002 году я получил воз-\nможность познакомиться с подлин-\nной рукописью в ОР РНБ, изучить\nпочерк и водяные знаки, увидеть\nдругие списки этого сочинения и\nокончательно утвердиться в своем\nмнении об авторстве Крекшина.\nТогда же я поделился своими на-\nблюдениями с хранителем рукописи\nПавлом Андреевичем Медведевым и\nпосоветовалему отметить авторство\nв описании рукописи. Вполне воз-\nможно, что оноставил предложения\nпровинциального историка без вни-\nмания. Зато Ю. Н. Беспятых, с ко-\nторым я поделился своей находкой,\nпредложил мне срочно подготовить\nстатью об авторстве сочинения для\nсборника «Феномен Петербурга»,\nчто мною и было сделано. Тогда же,\nв 2002 году, рукопись «О зачатии\nи здании…» была упомянута как\nсочинение П. Н. Крекшина в моей\nстатье об «Анекдотах» Я. Штелина8.\nВ 2003 году я выступил с докладом\n«Легенды об основании столицы\nРоссийской империи» в Школе\nвысших социальных исследований\nв Париже (русская секция).\nПока я дожидался выхода сбор-\nника «Феномен Петербурга» (он\nвышел только в 2006 году), в печати\nпоявилисьпубликациипетербургско-\nго историка П. А. Кротова на ту же\nтему10. Естественно, они привлекли\nмое внимание. О них, в частности, о\nкниге «Основание Санкт-Петербурга.\nЗагадки старинной рукописи» (СПб.,\n2006) мне и хотелось бы сказать не-\nсколько слов.\nЖиво и увлекательно автор изла-\nгаетисторию публикациии изучения\nстаринной рукописи об основании\nПетербурга. Правда, вывод Кротовао\nтом, что «к началу XXI века загадоч-\nная рукопись… по-прежнему строго\nхранит свои тайны», я разделить не\nмогу. Во-первых, потому что братья\n89\nИстория Петербурга. № 1 (47)/2009"
        },
        {
            "page": 1,
            "text": "ецензии книго Петербурге\nМ. И. и В. И. Семевские уже в XIX\nвеке догадывались о ее принадлеж-\nности П. Н. Крекшину, во-вторых, к\nначалу XXI века уже существовала\nмоя диссертационная работа. Ко-\nнечно, П. А. Кротов не обязан знать\nо ее существовании. Как остроумно\nзаметил В. О. Ключевский, диссерта-\nция - это труд, укоторого один автор\nи два читателя.\nСловно опытный «детектив-\nщик» П. А. Кротов постепенно под-\nмогу согласиться с мнением автора,\nчто сочинение «О зачатии и здании\nцарствующаго града Санктпетер-\nбурга» было создано в последние\nгоды жизни Крекшина. Это мнение\nне учитывает тот факт, что ранняя\nверсия сочинения, как было уже\nотмечено, содержится в составе\n«Краткого описания блаженных\nдел… Петра Великого», препод-\nнесенного императрице Елизавете\nПетровне в 1742 году.\nводит своего читателя к разгадке\nвремени создания и авторства сочи-\nнения о начале Санкт-Петербурга.\nОн приводит разные мнения, вы-\nсказанные ранее исследователями\nпо этому поводу. Вот, например,\nмосковский историк О. Г. Агеева\nрассматривает сочинение «О за-\nчатии и здании…» как «произведе-\nние неизвестного автора середины\n1720-х гг.»11. Но автор книги про-\nявляет непростительную забыв-\nчивость и не договаривает одну\nважную деталь: О. Г. Агеева при-\nводит эту датировку со ссылкой на\nстатью… П. А. Кротова 1991 года12.\nЭта же статья ввела в заблуждение\nи Е. А. Погосян13. Тогда, в начале\n1990-х годов, «глубокое источни-\nковедческое изучение» привело\nП. А. Кротова к выводу, что в тексте\nрукописи «имеются следы редакти-\nрования Петром I». Правда, автору\nпришлось проявить немалую наход-\nчивость, чтобы объяснить, как руко-\nпись с собственноручной правкой\nцаря может содержать известие о его\n(Петра I!) погребении. Чтобы при-\nдать своей тогдашней версии боль-\nшую убедительность, П. А. Кротов\nне полностью привел рукописную\nпомету XVIII века, имеющуюся на\nконволюте, в состав которого входит\nрукопись: «Сия книга из кабинета\nЕго императорского величества чер-\nныя бумаги относятся до основания\nСанкт-Петербурга и есть черные\nбумаги, которые поправляемы были\nсамим Государем Императором Пе-\nтром Великим». Пропустив в статье\n1991 года выделенные курсивом\nслова, П. А. Кротов настаивал на\nВольтер. Рис. А. С. Пушкина, 1836 г.\nэтотраз он пишет: «На самом деле в\nсборнике нет ни одной пометы руки\nПетра Великого, да и быть не могло:\nбумага всехего рукописей относится\nко второй половине XVIII века». Но\nцарские пометы там, кажется, все-\nтакиесть - нафинансовых бумагахс\nфилигранями Дудергофской фабри-\nки 1721-1727 годов, составляющих\nчетвертую часть конволюта.\nАнализ водяных знаков приво-\nдит П. А. Кротова к заключению,\nчто рукопись была создана в период\nс 1754 до начала 1760-х годов. Не\nоспаривая датировку рукописи, не\nLES\nGUVRES\nC O MPLETES\nD E\nVOLTAIRE\n46\nНесомненной заслугой П. А. Кро-\nтова является дополнение и уточ-\nнение биографии П. Н. Крекшина с\nпомощью документов Российского\nгосударственного архива Военно-\nморского флота. Попытка дать общую\nоценку историческому и литератур-\nному творчеству П. Н. Крекшина, на\nмой взгляд, удалась автору меньше.\nУбедительно представить Крекшина\nкак типичного автора эпических\nсочинений XVIII века невозможно.\nМногие исследователи справедливо\nуказывали на жанровый эклектизм\nписаний Крекшина, включавших\nразнородные элементы отжития до\nанекдота. Ксожалению, П. А. Кротов,\nпосвятивший одну из глав своей кни-\nги рассмотрению мнений историков\nи литературоведов о Крекшине, не\nупомянул здесь не только лучшие\nлитературоведческие работы о «нов-\nгородском баснословце», принадле-\nжащие перу М. Б. Плюхановой, но и\nтруды своих коллег по факультету14.\nСтремление поставить своего героя\nTHE\nCOMPLETE\nWORKS\nO F\nVOLTAIRE\n46\nпричастности царя к созданию\nрукописи. Между тем союз «и» в\nданном случае ясно указывает на то,\nчто черновые бумаги, относящиеся\nк истории Петербурга, и черновики,\nправленные Петром I, - это разные ча-\nсти конволюта. В своей новой работе\nавтор полностью отрицает наличие\nавтографов Петра I в сборнике. На\nOXFORD\n1999\nvoltaire foundatIon\noxford\n1999\nТитульный лист. т. 46. Полн. собр. соч. Вольтера (Оксфорд, 1999 г.)\n90\nИстория Петербурга. № 1 (47)/2009"
        },
        {
            "page": 2,
            "text": "ецензии книго Петербурге\nв один ряд с классиками эпического\nжанра - Гомером, Вергилием, Воль-\nтером - выглядит почти курьезно.\nЕще Е. Ф. Шмурло писал: «Крекшин\nи Вольтер! Что можно представить\nсебе более несходного, противо-\nречивого, даже уморительного при\nсопоставлении этих двухимен!»15. Не\nменее спорным является сближение\nП. Н. Крекшинас Н. М. Карамзиным.\nИ тот и другой пытались соединять\nисторию с литературой, но делали это\nразличными способами.\nНаконец, обратим внимание\nна то, что автор книги настойчиво\nпишет фамилию своего героя через\nбукву «ё» - Крёкшин, и даже обо-\nсновывает это ссылкой на «знато-\nков». Но дело в том, что буква «ё»\nвпервые была введена Н. М. Ка-\nрамзиным в 1796 году, поэтому мы\nне можем достоверно установить,\nкак произносилась фамилия наше-\nго героя в XVIII веке. Некоторую\nвозможность в этом плане может\nдать изучение топонимов Новго-\nродской области, в которой имеются\nнаселенные пункты с названием\n«Крекшино».\nВ конце своей книги П. А. Кро-\nтов возвращается к вопросу, как\nбыл заложен Санкт-Петербург.\nПрисутствовал ли Петр I на за-\nкладке города? Казалось бы, уста-\nновленный автором факт авторства\nП. Н. Крекшина должен стать допол-\nнительным аргументом для скепти-\nков, отрицающих личное участие\nцаря в закладке будущей столицы.\nВедь труд Крекшина - единствен-\nный источник, где говорится о при-\nсутствии царя на Заячьем острове\n16 мая 1703 года. Асовременники не\nзряхарактеризовали Крекшина как\n«враля». Признавая вымышленный,\nлитературный характер сочинения\nКрекшина, П. А. Кротов отрицает\nего значение как достоверного ис-\nточника о начале Петербурга. Но\nпри этом историк, как и Крекшин,\nнастаивает на присутствии царя при\nосновании Петербургской крепости.\nНе вдаваясь в полемикупоэтомуво-\nпросу, замечу, что в главном выводе\nкнигиможноразглядеть проявление\nтой же ложнопатриотической тен-\nденции, которая побуждала автора\nв 1991 году настаивать на причаст-\nности Пстра I к рукописи сочинсния\n«О зачатии и здании царствующаго\nграда Санктпетербурга».\nВ европейском масштабе среди\nпервых биографов Петра Великого\nИ. И. Голиков. Гравюра Розанова\nособое место принадлежит Вольтеру\n(1694-1778). По таланту и извест-\nности он резко выделялся среди\nевропейских историков, писавших\nтогда о русском царе, таких как\nЖ. Руссе де Мисси, Е. Мовийон и\nдр. Знаменитый француз нередко\nпозволял себе третировать своих\nпредшественников в описании дел\nПетра I. Исключение делалось для\nФонтенеля, автора «Похвального\nслова Петру Великому», - у него\nВольтер позаимствовал концепцию\nцаря-демиурга, «сотворившего но-\nвую нацию».\nПетру I Вольтер посвятил су-\nщественную часть своей «Истории\nКарла ХII» (1730-1731), а также\nдвухтомную «Историю Россий-\nской империи при Петре Великом»\n(1759-1763). Гораздо меньше из-\nвестно еще одно сочинение этого\nавтора: «Анекдоты о царе Петре\nВеликом», вышедшие в 1748 году.\nВольтеровские «Анекдоты» - это\nнесколько живо изложенных сю-\nжетов из жизни Петра I: царь,\nобучающийся в Голландии и Англии\nкораблестроению; введение табака\nв России и якобы вызванное этим\nстрелецкое восстание; бытовые и\nцерковные реформы Петра; история\nэстонской сироты, ставшей рус-\nской императрицей; дело царевича\nАлексея; визит Петра I в Париж.\nЭто сочинение лишь недавно было\nпереведено на русский язык.\nПервый перевод, сопровожден-\nный вступительной статьей и крат-\nкими комментариями, был опубли-\nкован мною в 2001 году16. Оставлю\nспециалистам судить о качестве\nпубликации. Зная о том, что над\nпереводом исторических трудов\nВольтера работает петербургский\nисторик С. Н. Искюль, я, естествен-\nно, послал ему экземпляр сборника\nс моим переводом.\n«Анекдоты» Вольтера в перево-\nде С. Н. Искюля вышли в 2006 году\nв 10-м выпуске альманаха «Русское\nпрошлое»17. Я с большим интересом\nпознакомился с работой известного\nисторика и профессионального\nпереводчика. Естественно, я ожидал\nувидеть в работе С. Н. Искюля если\nне оценку моего перевода, то хотя\nбы упоминание о нем. Однако во\nвводной заметке публикатора со всей\nопределенностью было сказано: «это\nсочинение по-русски не публикова-\nлось». Прочитав эту фразу, я понял\nсмысл устных извинений Сергея Ни-\nколаевича, высказанных при переда-\nче мне экземпляра альманаха.\nОднако не только задетое ав-\nторское самолюбие заставляет\nменя высказаться об этой работе.\nУдивляет то, что С. Н. Искюль\nдаже не посчитал нужным указать,\nкакое издание «Анекдотов» легло в\nоснову его перевода. Полагаю, что\nочень немногие читатели альмана-\nха могут догадаться об этом, ибо\nнемногие держали в руках 46-47\nтома оксфордского издания Пол-\nного собрания сочинений Вольтера\n(1999), где наряду с «Историей»\nПетра I помещены и «Анекдоты»18.\nКомментарии, в значительной\nстепени заимствованные из этого\nиздания, не оставляют сомнения в\nтом, каким источником пользовался\nпереводчик. К сожалению, и в рабо-\nте с комментариями Мишеля Мерво\nС. Н. Искюль допустил некоторую\nнебрежность. Искажено написание\nфамилии О. де ла Моттрея, сочине-\nнием которогопользовался Вольтер.\nГанноверский резидент в России\nФ. Х. Вебер назван голландским\nрезидентом. Когда комментатор\nговорит в частном случае о зависи-\nмости Вольтера от «Универсальной\nгеографии» И. Хюбнера, вышедшей\nв 1757 году, возникает недоумение:\nкак Вольтер мог воспользоваться\nкнигой за десять лет до ее изда-\nния. В комментариях М. Мерво по\nэтому поводу сделано уточнение: в\nбиблиотеке Вольтера имелось фран-\nцузское издание 1746 года.\nВызывает определенное недоу-\nмение и то, что, издавая «Анекдоты»\nВольтера, автор вступительной\nстатьи ничего не сказал о жанровой\n91\nИстория Петербурга. № 1 (47)/2009"
        },
        {
            "page": 3,
            "text": "ецензии книго Петербурге\nспецифике этоготипичнейшего для\nXVIII века сочинения. Между тем\nжанр анекдота, как его понимали в\nвеке Просвещения, в последнее вре-\nмя привлекал пристальное внима-\nние исследователей19. С. Н. Искюль\nобошел вниманием и содержатель-\nную статью Мишеля Мерво, специ-\nально посвященную «Анекдотам о\nцаре Петре Великом» Вольтера20 (ее\nсокращенный вариант опубликован\nи на русском языке21).\nНе подвергая сомнению пере-\nводческое мастерство С. Н. Искюля,\nпозволю себе усомниться в необхо-\nдимости искусственной архаизации\nязыка при переводе сочинения\nВольтера. Старинные словечки\nвроде «толико», «оные», «поелику»,\nконечно, отсылают нас к XVIII вску.\nНо вотличие отрусского литератур-\nного языка, правила и орфография\nкоторого только складывались в\nXVIII веке, французский язык Воль-\nтерабыл классически ясным, вполне\nсложившимся. Язык великого фран-\nцузского писателя отнюдь не был\nидентичен «голиковской прозе».\nНаконец, признавая превос-\nходство перевода С. Н. Искюля в\nодном-двух случаях, где имеются\nсмысловые расхожденияс моимтек-\nстом, немогусогласиться сего пере-\nводом фразы, касающейся судьбы\nпоследнего патриарха: «Ноне верно,\nчто царь, как о том говорили, поме-\nстил бывшего патриарха на покое в\nодном из скромных московских до-\nмов». Выражение «Petite-Maison de\nMoscou» в этом случае явно означа-\nет «Московский сумасшедший дом»\n(по аналогии с психиатрической\nлечебницей в Париже) и намекает на\n«Всешутейший и всепьянейший со-\nбор» царя Петра, в составе которого\nбыл шутовской «патриарх». Также\nне вполне оправданным кажется то,\nчто переводчик избегаетпереводить\nглагол «civiliser» современным сло-\nвом «цивилизовать». Ведь именно\nв середине XVIII века это слово\nприобретает во французском языке\nсвое современное значение: «при-\nобщение к цивилизации»22\nГоворя об «Анекдотах» Вольте-\nра, отметим, что из отечественных\nавторов едва ли не первым обратил\nна них внимание Н. А. Копанев на\nстраницах сборника «Петровское\nвремя в лицах»23. Можно согласиться\nс автором сообщения, что Петр I был\nописан в «Анекдотах» как человек\nжестокий, гневный, приверженный\nалкоголю, можно увидеть в этом\nсочинении Вольтера преувеличе-\nние исторической роли Лефорта,\nоднако назвать это сочинение «явно\nантипетровским», как это делает\nН. А. Копанев, все-таки нельзя.\nСвобода суждений, отсутствие\nидеализаторских намерений и не-\nкоторый скепсис в отношении\nуспехов «цивилизации» России\nчувствуются в «Анекдотах», конеч-\nно, больше, чем в «Истории Рос-\nсийской империи при Петре Вели-\nком». Однако, как справедливо заметил\nеще Е. Ф. Шмурло, вольтеровская кон-\nцепция царя-созидателя, положи-\nтельного героя, противостоявше-\nго завоевателю Карлу ХII, «творца\nсвоего народа» сложилась еще в\n«Истории Карла XII» ипобольшому\nсчету никогда не менялась. Правда\nсостоит и в том, что похвала париж-\nскихавтороввадрес Петра Iнередко\nпредставлялась петербургским па-\nтриотам елизаветинского времени\nхулой. Поэтому очень любопыт-\nным представляется приведенный\nH. А. Копаневым факт: «Гнев Ели-\nзаветы Петровны после публикации\n«Анекдотов» был столь велик, что\nв Петербурге долго искали и так\nи не нашли чиновника, виновного\nв избрании Вольтера в 1746 году\nпочетным членом Петербургской\nАкадемии наук». Жаль только, что\nсообщение уважаемого автора не\nимеет ссылок на источники.\nЕдинственным историком XVIII\nвека, которому удалось создать мак-\nсимально полное жизнеописание\nПетра I, был Иван Иванович Голи-\nков (1734-1801) - автор «Деяний\nПетра Великого, премудрого пре-\nобразителя России, собранных из\nдостоверных источников и располо-\nженных по годам» (М., 1788-1789.\nЧ. 1-12), которые вместе с «Допол-\nнением к Деяниям Петра Великого»\n(М., 1790-1797. Т. 1-18) составляют\n30 томов. В материалах конферен-\nции «Петровское время в лицах» за\n2003 год помещена статья Д. Д. Зе-\nлова, посвященная автору «Деяний\nПетра Великого»24. Хотелось бы раз-\nделить пафос автора, выступающего\nза признание серьезного научного\nзначения трудов И. И. Голикова,\nоднако проявившаяся в статье ме-\nтодика работы вызывает серьезные\nсомнения и заставляет спорить едва\nли не с каждым положением автора.\nБездоказательность, отсутствие в\nработе серьезной источниковой и\nисториографической базы слишком\nчасто приводятавторак ошибочным\nзаключениям. Вот лишь несколько\nпримеров.\nАвтор называет своего ге-\nроя «курским негоциантом», но\nИ. И. Голиков, хотя и был записан\nв курское купечество, уже с на-\nчала 1760-х годов принадлежал\nк богатой, политически актив-\nной части столичного купечества,\nимеющей широкие культурные\nинтересы. Крупные предприни-\nматели, государственные деятели,\nписатели, переводчики составляли\nкруг общения братьев Голиковых,\nраспоряжавшихся миллионными\nкапиталами.\nД. Д. Зелов (и не он один)\nслишком доверчиво относится\nк уничижительной самооценке\nГоликова, любившего повторять,\nчто он человек «неученый» и не\nимеет «дерзости присвоить себе\nимя историка». Сегодня говорить\nо том, что Голиков «никогда не был\nи не стремился стать профессио-\nнальным историком», по меньшей\nмере не исторично, ибо крупнейшие\nрусские историки второй половины\nXVIII века - М. М. Щербатов и\nИ. И. Болтин также были само-\nучками и дилетантами и в этом\nсмысле отличались от Голикова\nлишь знанием иностранных язы-\nков. Как писал В. О. Ключевский,\n«в то время, чтобы быть студентом\nрусской истории, необходимо было\nстать для самого себя профессором\nэтого предмета»25. Другой вопрос,\nкак далеко эти русские самоучки\nXVIII века продвигались в своей\nработе по сбору, систематизации и\nкритике источников, по осмысле-\nнию исторических событий. Этот\nвопрос в отношении 30-томного\nсочинения Голикова Д. Д. Зелов\nлишь едва наметил, констатируя\nжитийные приемы и старомодный\nпровиденциализм историка. Автор\nстатьи не проявил ни малейшего\nжелания опереться на наблюдения\nдругих исследователей. По его сло-\nвам, труды Голикова «практически\nне становились объектом изуче-\nния». Это утверждение далеко не\nсоответствует действительности.\nКроме моей монографии, вышедшей\nв 1991 году26, Голикову в разное вре-\nмя были посвящены (целиком или\nчастично) работы Е. Ф. Шмурло,\nИ. Л. Фейнберга, А. И. Фейнбер-\nга, В. М. Былова, В. С. Листова и\n92\nИстория Петербурга. № 1(47)/2009"
        },
        {
            "page": 4,
            "text": "ецензии книго Петербурге\nH. А. Тарховой, А. Т. Николаевой,\nМ. Б. Плюхановой, Н. Рязановского,\nА. Ю. Самарина, А. Н. Котлярова и\nГ. Н. Можаевой, А. Нефедова27, и\nдр. Кстати, некоторые ошибочные\nпассажи из популярной статьи\nA.Нефедова, кажется, перекочевали\nв работу Д. Д. Зелова.\nИсследователи по-разному оце-\nнивают научный уровень трудов\nИ. И. Голикова. Известный историк\nE. В. Анисимов без долгих разбира-\nтельств объявил Голикова графома-\nном и сумасшедшим (в качестве диа-\nгноза указано: «любовь» к Петру I)28.\nЯ же в результате изучения десятков\nтомов «голиковской прозы» вслед за\nA. Т. Николасвой склоняюсь к мне-\nнию, что И. И. Голиков за многие годы\nработы над жизнеописанием Петра I\nпрошел путь от доверчивого студента\nдо умудренного профессора, конечно\nже, по меркам XVIII века.\nНеточное название главного\nголиковского труда (Голиков назы-\nвал Петра преобразителем), ничем\nне обоснованное утверждение, что\nименно А. Р. Воронцов внес имя\nИ. И. Голикова в «список» амни-\nстируемых по случаю открытия\n«Медного всадника», утверждение,\nчто Голиков работал над своим сочи-\nнением только в сельце Анашкино, -\nэто лишь некоторые из мелких огре-\nхов работы Д. Д. Зелова. Вслед за\nА. Нефедовым, А. Н. Котляровым и\nГ. Н. Можаевой Д. Д. Зелов утверж-\nдает, что голиковское собрание книг\nи рукописей перешло В. Н. Кара-\nзину, а затем в Древлехранилище\nМ. П. Погодина. На самом деле,\nбольшая часть голиковского архива\nпогибла в огне пожара в имении\nпотомков историка29. В составе\nДревлехранилища Погодина и в не-\nкоторых других архивах, к сожале-\nнию, сохранились лишь единичные\nдокументы Голикова.\nОшибочным является утверж-\nдение Д. Д. Зелова (как и не-\nкоторых других авторов) о том,\nчто труд Голикова «получил вы-\nсочайшее одобрение Екатерины\nII». Имени императрицы не было\nсреди подписчиков на «Деяния»\nи «Дополнение». По этому поводу\nсам историк, нуждавшийся в ма-\nтериальной поддержке, с горечью\nписал: «песни русские и сказки\nмногие напечатаны на счет казны,\nв пользу издателей, … многие сти-\nхотворцы за одну оду, из несколь-\nких строк состоящую, получили и\nполучают награды, и напротив того\nна мои труды и сколькаго не об-\nращено внимания, чтобы сравнить\n3.\nих с сказками…»30\nСомнение вызывает утвержде-\nние Д. Д. Зелова, что как историк\nИ. И. Голиков шел по пути древне-\nрусских летописцев и агиографов.\nНесомненная идеализация Голико-\nвым своего «Ироя» еще не означает,\nчто 30-томное сочинение создано\nпо житийному канону. Это положе-\nние необходимо доказать. Сравне-\nние подходов Голикова с методами\nП. Н. Крекшина свидетельствует о\nтом, что историк второй половины\nXVIII века уже отошел от традиций\nдревнерусской литературы. Кроме\nтого, панегирист Голиков отнюдь не\nзамалчивал неудобных сторон дея-\nтельности царя, он брался за обсуж-\nдение таких вопросов петровского\nцарствования, цитировалтакие оцен-\nки царя, которые русская цензура не\nпропускала и в середине XIX века.\nНе отрицая элементов прови-\nденциализма в исторических взгля-\nдах автора «Деяний», следует со\nвсей определенностью сказать, что\nв целом исторические сочинения\nГоликова не были «созданы в духе\nсредневекового провиденциализ-\nма». Доказательства, приведенные\nД. Д. Зеловым в пользу этого мне-\nния, являются плодом недоразуме-\nния. Автор приписал И. И. Голикову\nвзгляды протоиерея П. А. Алексеева\nи ПI. Н. Крекшина. В своей книге\n«Сравнение свойств и дел Кон-\nстантина Великого с свойствами и\nделами Петра Великого» (М., 1810)\nГоликов критиковал записку Алек-\nсеева на эту тему и пришел к вполне\nрациональному выводу, что «сии два\nгосударя не могут… один с другим в\nсравнении быть»31.\nЗаключая этот ряд «сердца го-\nрестных замет», хотелось бы сказать,\nчто в современной историографиче-\nской ситуации, когда, с одной сто-\nроны, российская наука становится\nчастью мировой, а с другой стороны,\nрастет поток малотиражных публи-\nкаций, которые не всегда доходят до\nбиблиотек и специалистов, вопрос о\nнаучной этике исследователя приоб-\nретает особое значение. Отсутствие\nофициальной цензуры и тематиче-\nских ограничений с новой остротой\nставят проблемы внутренней цензуры\nавтора, егответственности перед\nчитателями и коллегами. Локальная\nограниченность и провинциальное са-\nмодовольство совсем не к лицу исто-\nрикам Петербурга - города, который\nвсегда был открыт стране и миру.\n1 РГАДА. ГА. Ф. 17. Д. 167. Это наиболее изученное сочинение П. Н. Крекшина. О нем см.: Шмурло Е. Ф. Петр Великий в оценке\nсовременников и потомства. СПб., 1912. С. 48-49, 53-64 (прим.); Николаева М. В. Из истории русской повествовательной литерату-\nры первой половины XVIII века («Сказание о Петре Великом» П. Н. Крекшина) // Учен. зап. Лен. гос. пед. ин-та им. Герцена. 1958.\nТ. 170; Колосова Е. В. К проблеме традиции древнерусской исторической повести в литературе XVIII века («Сказание» П. Н. Крекшина\nо Петре I как последний этап развития исторической повести XVII века) // Древнерусская литература и ее связи с новым временем.\nМ., 1967; Плюханова М. Б. «Историческое» и «мифологическое» в ранних биографиях Петра Первого // Вторичные моделирующие\nсистемы. Тарту, 1979; Ее же. История юности Петра I у П. Н. Крекшина // Учен. зап. Тартуск. гос. ун-та. 1981. Вып. 513; Ее же. К про-\nблеме изучения историографического наследия П. Н. Крекшина //М. В. Ломоносов и русская культура. Тезисы докладов конференции.\nТарту, 1986.\n2 Г. Ф. Миллер сообщал, что крекшинская история Петра, написанная в форме дневника, состоит из пятнадцати фолиантов. См.:\nПекарский П. П. История имп. Академии наук. СПб., 1870. Т. 1. С. 344.\n3 ОР РНБ. Погодин. № 1731.\n4 ОP РНБ. IV. № 864.\n5 Беспятых Ю. Н. Петербург Петра I в иностранных описаниях. Л., 1991. Приложение 2. С. 258-262 .\n6 РГАДА. ГА. Ф. 17. Д. 167. Л. 399 об.-404 об.\n7 Мезин С. А. Петр I в общественной мысли XVIII века: Россия и Франция: Автореф. дис… д-ра ист. наук. Саратов, 1999. С. 14.\n8 Мезин С. А. Анекдоты о Петре Великом как явление русской историографии XVIII в. // Историографический сборник. Саратов,\n2002. Вып. 20. С. 51.\n93\nИстория Петербурга. № 1 (47)/2009"
        },
        {
            "page": 5,
            "text": "ецензии книго Петербурге\n9 Мезин С. А. Об авторстве сочинения «О зачатии и здании царствующаго града Санктпетербурга» // Феномен Петербурга. Тру-\nды Третьей Международной конференции, состоявшейся 20-24 августа 2001 года во Всероссийском музее А. С. Пушкина / Отв. ред.\nЮ. Н. Беспятых. СПб., 2006. С. 289-307 .\n10 Кротов П. А. Начало Санкт-Петербурга: тайны старинной рукописи // Меншиковские чтения - 2005. СПб., 2005. С. 66-95;\nКротов П. А. Основание Санкт-Петербурга: загадки старинной рукописи. СПб., 2006.\n11 Агеева О. Г.\n«Величайший\nи\nславнейший более всех градов в свете» - град Святого Петра: Петербург в русском\nобщественном\nсознапии начала XVIII века. СПб., 1999. С. 60-61, 266-267 .\n12 Кротов П. А. Рождение Балтийского военно-морского флота // Вопросы истории. 1991. № 11. С. 211-213 .\n13 Погосян Е. А. Петр I - архитектор российской истории. СПб., 2001. С. 232-233 .\n14 Кривошеев Ю. В., Фещенко Л. Г. Некоторые древнерусские источники повести о начале Петербурга // Спорные проблемы истории\nрусской общественной мысли (до начала XIX века). Тез. докл. конф. М., 1992. С. 35-37; Дворниченко А. Ю., Кривошеев Ю. В. Древнерусские\nисточники\nповести о начале\nПетербурга // Петербургские чтения. К юбилею города. Тез. докл. конф. СПб., 1992. С. 51-54.\n15 Шмурло Е. Ф. Указ. соч. С. 49.\n16 Вольтер. Анекдоты о царе Петре Великом\n/ Пер. с фр.,\nкоммент. и вступ.\nст. С.\nА. Мезина // Историографический\nсборник.\nСаратов, 2001. Вып. 19. С. 184-199 .\n17 Вольтер. Анекдоты о царе Петре Великом / Пер. с фр., вступ. ст. и коммент. С. Н. Искюля // Русское прошлое. Историко-\nдокументальный альманах.\nСПб., 2006. Кн. 10. С. 7-26.\n18 Oeuvres complètes de Voltaire. Oxford, 1999. Vol. 46. P. 51-84.\n19 Курганов\nЕ.\nАнекдот как жанр. СПб., 1997; Чекунова А. Е. Появление исторического анекдота в России // Вопросы истории.\n1997. № 2; Никанорова Е. К. Исторический анекдот в русской литературе XVIII века. Анекдоты о Петре Великом. Новосибирск, 2001;\nМезин С. А. Анекдоты о Петре Великом как явление русской историографии XVIII века // Историографический сборник. Саратов,\n2002. Вып. 20, и др.\n20 Mervaud M. Les Anecdotes sur le czar Pierre le Grand de Voltaire: genèse, sources, forme littéraire // Studies on Voltaire and eighteenth\ncentury. 1996. Vol. 341.\n21 Мерво М.\n«Анекдоты о царе Петре Великом»: генезис, источники и жанр // Вольтер в России. М., 1999.\n22 Например: Годжи Д. Колонизация и цивилизация: русская модель глазами Дидро // Европейское Просвещение\nи цивилизация\nРоссии. М., 2004.\n23 Копанев Н. А. Петр I и Ф. Лефорт в исторических сочинениях Вольтера // Петровское время в лицах. СПб., 1998. С. 23-25.\n24 Зелов Д. Д. «Деяния Петра Великого, мудрого преобразователя России» И. И. Голикова (к вопросууоб обстоятельствах создания\nи современном научном значении) // Петровское время в лицах - 2003. СПб., 2003. С. 52-59.\n25 Ключевский В.О. Сочинения: В 9 т. М., 1989. Т. 7. С. 235.\n26 Мезин С. А. Русский историк И. И. Голиков. Саратов, 1991.\n27 Шмурло Е. Ф. Петр Великий в оценке современников и потомства. СПб., 1912. С. 91-95, 95-97 (прим.); Фейнберг И. Л. Читая\nтетради Пушкина. М., 1985. С. 10-120; Фейнберг А. И. Заметки о «Медном всаднике». М., 1993; Былов В. М. «Деяния Петра Велико-\nго» И. И. Голикова как материал для изучения фольклора XVIII века // Русский фольклор. Материалы и исследования. М.; Л., 1959.\nТ. 4; Листов В. С., Тархова Н. А. Труд Голикова «Деяния Петра Великого» в кругу источников трагедии «Борис Годунов» // Времен-\nник Пушкинской комиссии. 1980. Л., 1983; Тархова Н. А. «Благородный и простодушный труд Голикова» // Альманах библиофила.\nМ., 1984. Вып. 16; Николаева А. Т. Вопросы источниковедения в трудах И. И. Голикова, посвященных Петру I // Труды Моск. Гос.\nисторико-архивн. ин-та. Т. 24. Вып. 2. М., 1966; Плюханова М. Б. Голиков Иван Иванович // Словарь русских писателей XVIII века.\nЛ., 1988. Вып. 1; Riasanovsky N. V. The Image of Peter the Great in Russian History and Thought. New York, Oxford, 1985. P. 43-44; Сама-\nрин А. Ю. Читатель в России во второй половине XVIII века (по спискам подписчиков). М., 2000. С. 171-173 ; Курские купцы Голиковы:\nОт монастырских бобылей до потомственных дворян. СПб., 2003; Котляров А. Н., Можаева Г. В. Иван Иванович Голиков (1734-1801)\n// Историки России XVIII-XХ веков. М., 1996. Вып. 3. (Архивно-информационный бюллетень. № 14);Нефедов А. Деяния Ивана\nГоликова, курского купца и звенигородского отшельника // Памятники Отечества. № 31 (1994. № 1-2).\n28 Петр Великий. Воспоминания. Дневниковые записи. Анекдоты. М., 1993. С. 367, 369.\n20 Лосиевский И. Я. Судьба голиковского собрания // В мире книг. 1982. № 4.\n30 Архив князя Воронцова. М., 1880. Кн. 24. С. 237.\n31 Мезин С. А. Русский историк И. И. Голиков. С. 66-67.\n94\nИстория Петербурга. №1 (47)/2009"
        },
        {
            "page": 6,
            "text": "ецензии книго Петербурге\nСолдаты тоже людн\nФаниил Уранин\n*\nо немецком романе «Маленький Кваст»*\nЮ. М. Лебедев\nВ 2004 году немецкий писатель\nХассо Стахов обратился ко мне с\nнеобычной просьбой. Переиздавал-\nся его роман «Маленький Кваст»,\nгде он рассказывал о себе в третьем\nлице, как о солдате немецкой 18-й\nармии, воевавшем под. Ленинградом.\nСтахов хотел, чтобы предисловие к\nновому изданию романа написал\nДаниил Гранин, автор «Блокадной\nкниги», сам сражавшийся с нем-\nцами в народном ополчении у стен\nЛенинграда.\nПросьба эта, признаюсь, по-\nставила меня в тупик. Я сразу же\nрешил, что она несбыточна, в пер-\nвую очередь потому, что этот роман\nникогда прежде не издавался на рус-\nском языке. В Европе, Америке его\nхорошо знают с 80-х годов, именно\nтогда он вызвал большой междуна-\nродный резонанс своей антивоенной\nнаправленностью. Но в Советском\nСоюзе онбыл невозможен, посколь-\nкуавтор был из капиталистической\nЗападной Германии, явно не по-\nсыпал голову пеплом, описывая\nбоевые действия под Ленинградом,\nто есть не раскаивался. Книга была\nнаправлена против войны, но она\nодновременно защищала немецкого\nсолдата, ставшего инструментом\nпреступной политики Гитлера. Бо-\nлее того, Стахов заявлял, что выпол-\nнял свой солдатский долг до конца:\nсначала в силу убеждения в правоте\nприказа, а затем просто потому, что\nэтот приказ никто не отменял. Хотя\nСоветского Союза уже не было поч-\nти 15 лет, тем не менее идеология\nэтого периода о немецких солдатах,\nкак о фашистах, еще прочно сидела\nв головах, в первую очередь людей\nстаршего поколения. Для книги\nСтахова время еще не пришло.\nНо была и еще одна причина\nчисто технического характера. Как\n* Иллюстрации к статье - Н. И. Шарф.\nмог Гранин написать предисловие\nк книге, которую он не читал, да\nи прочитать не мог, поскольку не\nвладеет в достаточной степени не-\nмецким языком?\nЯ попытался было довести все\nэтидоводы до Хассо Стахова, но тот\nупорно настаивал на своем. Мнение\nДаниила Гранина было для него\nопределяющим среди других рус-\nских людей. На его рассказ «Плен-\nные» Стахов ссылался в другой сво-\nей книге «Трагедия на Неве», то есть\nон знал и высоко ценил творчество\nнашего питерского писателя.\nВозможно,\nя\nбы так и не усту-\nпил его просьбе, но Стахов сразил\nменя одним своим аргументом. Он\nрассказал, почему пришел к напи-\nсанию романа «Маленький Кваст».\nВ 70-х годах он выступал в одной из\nвузовских аудиторий Германии. Все\nшло хорошо до того момента, пока\nразговор со студентами не коснулся\nвойны. Немецкая молодежь к тому\nвремени была сильно наэлектри-\nзована идеей всегерманского по-\nкаяния за преступления военного\nпоколения. В памяти увсех незабы-\nваемым оставался акт преклонения\nколеней канцлером Германии Вилли\nБрандтом у стен Варшавского гет-\nто в 1970 году. Многие писатели,\nтакие, как Гюнтер Грасс, эту идею\nпокаяния активно подняли на щит\nв своих произведениях. Поколение\nотцов стали напрямую нызывать\nпреступным. Поэтому студенты с\nходу задали Стахову вопрос, како-\nго года рождения он был? Стахов\nответил: 1924 года. После этого\nмежду ним и аудиторией возникла\nстена враждебности. Не помогали\nникакие аргументы. Студенты не\nжелалиегоослушать. Для нихон был\nсолдатом-нацистом.\nИ тогда Стахов решил ответить\nим книгой. Так возник роман «Ма-\nленький Кваст». Этотаргумент стал\nдля меня определяющим, поскольку\nроман я читал и был под большим\nвпечатлением от него. Были даже\nмысли его перевести, но отпугивало\nто, что литературным переводом\n95\nИстория Петербурга. № 1 (47)/2009"
        },
        {
            "page": 7,
            "text": "ецензии книго Петербурге\nна тот момент я вообще не владел.\nБыл, правда, профессиональным\nпереводчиком, но военным, а не\nлитературным.\nДаниилу Александровичу зво-\nнил я в этот раз без особого на то\nжелания. Почему-то был убежден,\nчто он меня отбреет, сказав, что само\nпо себе предложение нелепое. Но в\nочередной раз Гранин изумил меня\nсвоей непредсказуемостью. Просто\nсказал: «Приезжайте и расскажите\nмне об этой книге». Здесь необходи-\nмо небольшое дополнение. Дело в\nтом, что со Стаховым Гранин к тому\nвремени уже былзнаком. Не лично, а\nчерезего другую книгу подназванием\n«Трагедия на Неве». В переводе по\nглавам я посылал ему из месяца в\nмесяц рукопись. Видимо, книга его\nзаинтересовала, равно как и сам ее\nавтор. Теперь уже Гранин поставил\nменя в тупик своим предложением.\nКак можно пересказать книгу за\nкакой-то час? А вдруг я что-то не так\nв ней понял и навяжусвое ошибочное\nвосприятие известному писателю.\nНадо было как-то выходить из этой\nщекотливой ситуации. Решилеще раз\nперечитать роман уже с карандашом\nв руке, стараясь найти в нем наиболее\nзначимые смысловые места. Мне\nкажется, что это в конце концов уда-\nбенно вкусно выговаривает Гранин\nв таких случаях. Это его слово. Для\nменя такие прогулки с ним это одно-\nвременно наслаждение и мучение.\nПервое - это радостное чувство от\nтого, что общаешься действительно\nс великим человеком, обогащаясь\nежеминутно от него. Но с другой\nстороны, он буквально выворачи-\nвает тебя наизнанку своими вопро-\nсами, и ты, сам того не осознавая,\nраскрываешься перед ним в том\nаспекте, который ему необходим на\nданный момент.\nВ этот раз Гранин прогулял\nменя до галантерейного магазина в\nсторону «Авроры». Петроградская\nсторона, где он живет уже многие\nгоды, одно из любимых мест его\nПетербурга. Большинство из нас\nходят по этим улицам, не замечая\nих очарования. Гранин гуляет с на-\nслаждением. И это чувство, когда\nидешь вместе с ним, вдруг передает-\nся и тебе. Во всяком случае, со мною\nтак бывало всегда. За те полчаса,\nчто мы шли до магазина то ли за\nрубашкой, то ли за носками: точно\nне помню, знаю, что ничего Гранин\nтак и не купил, он терпеливо, не\nпрерывая меня ни словом, выслу-\nшивал мой страстный гимн в защиту\n«Маленького Кваста». На обратном\nлось. Выбрав два из таких эпизодов,\nпути говорил уже он, но на другие\nя перевелих ина встречус Граниным темы, с романом было покончено.\nшел уже более уверенно.\nНа прощание перед его домом я\nТут необходимо еще одно отсту-\nпередал ему несколько листков с\nпление. Думаю, со мною согласятся\nдвумя переведенными эпизодами.\nте, кто имел счастье, а именно так я\nНа том с ним и расстался, так и не\nбы хотел определить это чувство,\nполучив ответа на просьбу Стахова.\nгулять с Даниилом Граниным. Я\nЯпонимал, что, видимо, мой рассказ\nспециально употребляю слово\nне впечатлил Даниила Александро-\n«гулять», так как именно его осо-\nвича, поэтому надежда оставалась\nтолько на содержание эпизодов. Вот\nчто в них было.\nЭпизод первый\nОднажды после обеда Хаберле\nотдал распоряжение: «Через час\nпьянка. Форма одежды - белый\nсмокинг ценителя спиртного».\nЭто означало, что они должны\nбыли вывернуть на грязно-белую\nсторонусвои маскхалаты. Были от-\nкрыты банки сардин, нарезан хлеб и\nсало. На стол поставлены персики,\nвымоченные в водке, а также дья-\nвольский напиток под названием\n«Яд из дремучего леса».\nВ качестве гостей были при-\nглашены: обер-ефрейтор Михель,\n«поскольку он образцово научил\nефрейтора Кваста стрелять из пу-\nлемета «МГ-34», и тому удалось по-\nдавить пулеметное гнездо русских».\nКроме него был приглашен один из\nкомандиров разведгруппы из второй\nроты в награду «за его высказывание\nо\nтом, что благодаря разведданным\nгруппы перехватателефонных пере-\nговоров уцелело не менее полуроты\nсолдат». Хассель самлично разнес и\nвручил эти приглашения.\nБлиже к вечеру все сели за стол.\nНачало было положено стаканом\nводки. Затем Хеберле открыл так на-\nзываемое «слушание Дела». Сперва\nбыли распределены роли: Хеберле\nбыл судьей, Хассель и Занд - при-\nсяжными, Хапф - обвинителем, а\nКваст - защитником. Переводчики\nвыступалисвидетелями, агости - пу-\nбликой. Обвиняемый отсутствовал.\nЭто был русский Иван. Причина его\nотсутствия была признана уважи-\nтельной: «вследствие труднопрео-\nдолимых условий местности». Его\nинтересы представлял Кваст.\nОбвинение гласило: Иван пред-\nнамеренно мешает пребыванию\nна свежем воздухе в летнее время.\nОн препятствует приему пищи в\nустановленные часы, легкомыслен-\nно обращаясь при этом со своим\nоружием. Он производит бессмыс-\nленный шум. Коварно использует\nдьявольскую силу десятков мил-\nлионов большевистских комаров,\nкоторые в летнюю пору посягают\nна самое ценное, что только есть в\nмире: на немецкую кровь!\nЧем больше было выпито, тем\nбессмысленнее становились изре-\nчения, которые во всю силу своих\nлегких выкрикивали представители\n96\nИстория Петербурга. № 1 (47)/2009"
        },
        {
            "page": 8,
            "text": "ецензии книго Петербурге\nболотной юстиции. Аргументы Ква-\nста в оправдание действий русских\nвоспринимались обвинителем как\nгосударственная измена. Публика\nи присяжные почти падали со ска-\nмеек от смеха и восторга. Хеберле\nс ревом нападал на Хапфа: «Если\nвы и дальше будете так неуклюже\nвыдвигать свои обвинения, то я\nоправдаю Ивана, и мы все пойдем\nдомой!» На это фельдфебель еле\nразборчиво лепетал: «Это хорошо.\nТак ли нам нужен этот Ленинград?\nДавайте спросим честно, что мы во-\nобще забыли в этой России?» Занд\nпоучительно заметил: «Водку!»\nХеберле набросился с упрсками\nна Кваста: «При чем тут Бисмарк?\nИ Йорк? Вы прибегаете к про-\nпагандистским лозунгам в защиту\nКрасной армии, вы комиссар!» А\nХассель угрожающе воскликнул:\n«Что подумает о вас фюрер, това-\nрищ Квастов?» Михель заорал: «Я\nне вижу никакого фюрера. Кто-\nнибудь видит здесь фюрера? Я\nполагаю, что он ищет свою войну.\nНо он даже в самом дерьмовом\nместе не в состоянии ее отыскать!»\nЛивен закричал: «Ты сказал, что он\nее потерял?» На это Михель: «Я?\nЭто сказал ты сам своим языком\nбез костей! Ребята, дайте Ливену\nчто-нибудь выпить, пока глотка у\nнего еще работает!»\nНаконец Хеберле вынес ре-\nшение относительно Ивана: «Наш\nсобрат по болотной жизни приго-\nваривается к запрету на стрельбу.\nОн должен немедленно представить\nнам своих телефонисток!» С этими\nсловами Хеберле, качаясь, под-\nнялся, криво нахлобучил на голову\nпилотку и, пробурчав: «Я скажу ему\nэто сам», вывалился за дверь.\nКваст быстро бросил изумлен-\nной пьяной компании: «Так мы его\nздесь враз потеряем, если вовремя не\nостановим!» Шатаясь, они вывали-\nлись другза другомнаружу. Хеберле\nвзобрался на крышу блиндажа. Те-\nперь он стоял там, выпрямившись\nс расставленными руками, и соби-\nрался начать речь. Хассель и Кваст\nрванули его за ноги. Как мешок он\nсвалился в проход. С улюлюканьем\nодин за другим они попадали вслед\nза ним в узкую траншею. И в то же\nсамос время по меньшей мере три\nпулемета открыли по ним огонь.\nИкая, Хаберле, пробормотал: «Иван\nнарушил правила игры. Полное бес-\nкультурье!»\nЭпизод второй\n…Перед входом на пост охра-\nнения из грязи торчит высокий\nпень. Раздатчик еды, неотесанный,\nглуповатый парень, бросает на него\nтермос с едой и открывает крышку.\nНа дне лежат порции бутербродов\nс тонким слоем маргарина, на зато\nна них положена толщиной в палец\nбледно-розовая «резиновая» колба-\nса. Раздатчик кричит: «Можно брать\nпо три порции. Теперь еды хватит\nна всех».\nКваст чувствует растущую тош-\nноту и ярость. Не потому, что этот\nпарень с таким циничным равноду-\nшием воспринимает потери послед-\nних часов. И не из-за того, что эта\nеда\nне вызывает у него аппетита.\nНо всего лишь в нескольких\nметрах от пня, раскинув руки,\nлежит убитый солдат из русской\nштурмовой роты, которой удалось\nпрорваться до самой железнодорож-\nной насыпи, где она все-таки была\nостановлена убийственным огнем\nоборонявшихся немецких солдат.\nГренадеры обороняли насыпь также\nи с обратного ее ската, ведя огонь из\nзамаскированных амбразур, устро-\nенных в лесных укрытиях.\nКваст медленно отодвигает в\nсторону кусок «резиновой» кол-\nбасы и в оцепенении смотрит на\nрусского. Перед ним лежит юноша с\nпрекрасным утонченным профилем.\nСветлые густые волосы покрыты\nзапекшейся кровью. Тонкий нос\nкажется прозрачным. Пустые глаза\nнаправлены на розовато-синее ве-\nчернее небо, по которому медленно\nплывут белые облака, напоминаю-\nщие своими очертаниями корабли.\nУзкие детские пальчики все еще\nсудорожно охватывают винтовку с\nгрубо обтесанным прикладом. Жук\nосторожно, на ощупь пробирается\nчерез бледно-желтую ушную рако-\nвину. Губы выглядят блеклыми на\nфоне контрастной белизны лица,\nверхняя губа немного приподнята.\nКвасту кажется, что он ощущает то\nупоение, которое испытывал юноша\nв момент броска через насыпь. Гор-\nдость от чувства, что он первым во-\nрвется на немецкие позиции. Ужас\nв тот момент, когда он внезапно\nосознал, что вместе с другими свои-\nми товарищами попадет под пере-\nкрестный огонь. В последний миг\nпонимание предстоящей смерти.\nКваст видит\nсебя самого, лежа-\nщего там. Он думает: русский выгля-\nдит, как любой из моих однокласс-\nников, так, будто я вместе с ним\nходил в школу и мы вместе играли\nв футбол. Кроме военной формы, их\nничего более не отличает.\nРусские являются недочеловека-\nми? Те, что сейчас сидят в Германии,\nне имеют об этом ни малейшего\nпредставления, продолжает размыш-\nлять Кваст. Егохватывает горечь, к\nкоторой примешивается злость. И\nкогда он, стиснув зубы, идет к себе\nв блиндаж и молча садится у стены,\nто не может избавиться от мучитель-\nного вопроса, а правильно ли он все\nоценивает? Этот юный русский ему\nнамного ближе, чем такое дерьмо, как\nгосподин полковник Гайершнабель,\nгосподин обер-лейтенант Эльберг,\nгосподин штабс-вахтмейстер Шак\nили господин хауптвахтмейстер\nБригель.\nГраница понимания всего это-\nго находится не на переднем крае\n97\nИстория Петербурга. № 1(47)/2009"
        },
        {
            "page": 9,
            "text": "ецензии книго Петербурге\nбоевых действий. Реальная граница\nпроходит совсем в другом месте.\nЧерез несколько дней раздался\nтелефонный звонок. Гранин, как\nвсегда, был конкретен: «Приез-\nжайте, я подготовил предисловие».\nПо своей военной привычке, как\nбывший офицер информационно-\nаналитических структур, ехал я на\nэтувстречуподготовленным. Взялс\nсобой не только бумагу для записи,\nно и диктофон. Как оказалось, не\nзря. Даниил Александрович усадил\nменя в кресло, сел напротив, и сра-\nзу же приступил к делу. Никакого\nтекста не было. Гранин просто раз-\nмышлял вслух. По существу он вел\nбеседу, но не со мной, асо Стаховым.\nЭто был их разговор, в котором мнс\nбыла отведена роль летописца и\nпереводчика. Вот что сказал солдат\nВторой мировой войны своему\nбывшему недругу и сегодняшнему\nсоратнику-гуманисту по писатель-\nскому ремеслу:\n«Воспоминаний немецких сол-\nдат о Второй мировой войне на-\nписано множество. Среди них есть\nкниги и тех, кто участвовал в бло-\nкаде Ленинграда: кто стрелял по\nгороду и кто бомбил его в течение\n1941-1944 годов.\nКнига Хассо Г. Стахова «Малень-\nкий Кваст» была для меня особенно\nинтересной, потому что он воевал\nпримерно на том же участке фронта,\nчто и я, но с другой стороны.\nНо не это главное. Признаюсь,\nчто я и до Стахова встречал и в\nлитературе, да и в жизни немцев,\nкоторые стояли напротив наших\nпозиций, стреляли в нас, так же как\nи мы в них.\nКнига Стахова была для меня\nзамечательной не просто этим со-\nвпадением. Пожалуй, впервые я\nстолкнулся с тем, что немецкий\nсолдат, который был для меня\nмишенью, всего лишь врагом, -\nоказался к тому же и человеком.\nОн размышляет, старается понять,\nчто это за война, зачем она нужна, в\nтом числе и лично ему. Там, на той\nстороне тоже смеются, отпускают\nшутки по поводу Ивана, как и мы\nшутили по поводу Фрица. Мерзнут\nдо обморожений, пишут письма,\nждут их от родных и близких.\nЧем дальше читаешь, тем боль-\nше это сходство завораживает.\nСейчас, спустя 60 лет после той\nвойны, может быть, это открытие\nпокажется не столь уже большим\nоткровением. Но в нашей совет-\nской и постсоветской литературе\nмы никогда не пытались увидеть\nв немецком солдате человеческое\nсущество, столь схожее с нашей\nсолдатской жизнью. Те же чувства,\nте же невзгоды и ту же страдающую\nплоть.\nМожет быть, еще лет тридцать\nназад я бы не воспринял подобный\nрассказ так, как воспринимаю сегод-\nня. Это не примирение, это скорее\nпонимание. И еще это узнавание. Че-\nрез героя книги я вспоминаю и себя,\nузнаю и свои фронтовые будни.\nОтчасти, конечно, чудо, что\nмы оба, рядовые солдаты, выжили,\nуцелели в этой мясорубке.\nИменно солдатское мировос-\nприятие той войны под Ленин-\nградом для меня особенно важно.\nРядовой солдат, такой же, как и я,\nзачастую вынужденный служить\nлишь пушечным мясом - это сход-\nство особенно удивляет. Конечно,\nпри всей непримиримости, во вся-\nком случае моей, к тем оккупантам,\nкоторые обрекали Ленинград на\nголодную смерть.\nОказывается, у немецких солдат\nбыли жены, матери, была любовь,\nтоска. Там были не только нацисты.\nТам были жертвы. Они погибали\nтак же, как умирали мои однопол-\nчане, так же в ужасе прижимались\nк земле во время артиллерийских\nобстрелов. Пусть к чужой земле, но\nища у нее защиты.\nСтахов был добровольцем, так\nже как и я. У нас была разная идео-\nлогия. Но если бы нас обоих убило,\nнашикостиодинаково гнили бы под\nЛенинградом.\nНаверное, наш страх и ужас\nперед летящим снарядом был тоже\nодинаков.\nЯ думаю, что такие книги, как\n«Маленький Кваст», нужны и се-\nгодня. В них дорого общечеловече-\nское начало. И тот давний вывод,\nкоторый никак не может усвоить\nчеловечество: захватнические вой-\nны - бессмысленны».\nВ 2005 году роман «Маленький\nКваст» вновь появился на при-\nлавках книжных магазинов Герма-\nнии. На этот раз с предисловием\nзнаменитого русского писателя.\nДля меня этот факт стал еще одной\nАкцией примирения в мучитель-\nном процессе преодоления вражды\nмежду нашими странами, которая\nна долгие годы ненавистью разде-\nлила поколения людей, воевавших\nмежду собой.\nКнига эта стоит у меня дома на\nвидном месте. Она словно призы-\nвает своим присутствием: «Может\nбыть, ты все-таки решишься на\nперевод? Ведь первый шаг пре-\nдисловием Гранина уже сделан. По\nсуществу, он благословил тебя на\nэто начинание».\nВозможно, в скором времени\nэто действительно произойдет. Же-\nлание, во всяком случае, становится\nвсе более острым.\n98\nИстория Петербурга. № 1 (47)/2009"
        },
        {
            "page": 10,
            "text": "ецензии книго Петербурге\nВ.К. Шуйский\nОГЮСТ\nМОНФЕРРАН\nИстория жизни и творчества\nB. Е. Павлов\nПамяти\n18. K Шуйскoг\nО многообразии деятельности\nО. Монферрана и его способностях\nкак зодчего, рисовальщика, акваре-\nлиста, медальера и коллекционера\nВ. К. Шуйский рассказывал с огром-\nным воодушевлением на различных\nконференциях и семинарах, на пре-\nзентациях книг и защитах диссерта-\nций по истории архитектуры.\n7 января 2008 года на 69 году\nжизни перестало биться сердце\nнеутомимого исследователя изнато-\nка архитектуры Санкт-Петербурга\nВалерия Константиновича Шуй-\nского.\nПеру В. К. Шуйского при-\nнадлежат монографии и статьи,\nопубликованные в разных источ-\nниках, посвященные зодчим А. За-\nхарову, В. Бренне, О. Монферрану,\nA. Штакеншнейдеру, Томаде Томону,\nК. Росси, Л. Кленце, трем Адамини.\nОсобенно значительной стала\nего монография, изданная в 2005\nгоду, - «ОгюстМонферран.История\nжизни и творчества» (см. рецензию\n«Славный и незабвенный Огюст\nМонферран» в журнале «История\nПетербурга». № 4 (32). 2006 г.).\nB. К. Шуйский закончил\nВоенно-механический институт\nв Ленинграде, получив диплом\nинженера, а затем Академию худо-\nжеств (Институт им. Репина), став\nспециалистом в области истории\nархитектуры. Много летон работал\nв Научно-исследовательском музее\nАкадемии художеств. Изучив мало-\nизвестные страницы деятельности\nкрупных зодчих, их замыслы и реа-\nлизованные проекты, В. К. Шуйский\nзащитил диссертацию на соискание\nученой степени кандидата искус-\nствоведения. Это позволило ему\nокунуться в сферу архитектуры\nСанкт-Петербурга XVIII - первой\nполовины XIX века.\nЖивой, образный язык, про-\nникновение в тончайшие формы\nзодчества, точные и содержатель-\nные определения и характеристики\nархитектурных элементов сооруже-\nния, показ каждого шедевра архи-\nтектуры в его историческом разви-\nтии, объективная оценка личности и\nзначения того или иного архитек-\nтора в области архитектуры - все\nэто характеризует В. К. Шуйского\nкак непревзойденного изыскателя\nи оригинального мыслителя на-\nшего времени. Отдавая должное\nсвоему любимому архитектору\nО. Монферрану, В. К. Шуйский на\nоснове многочисленных материалов\nорганизовал в 1986 году выставку,\nпосвященную 200-летию со дня\nрождения зодчего.\nВ 1986 году он побывал во\nФранции и подвиг специалиста\nпо франко-русским культурным\nсвязям Б. Н. Лосского на поиски\nмогилы О. Монферрана. Удалось\nточно установить, что зодчий был\nзахоронен на Монмартском кладби-\nще рядом с матерью, умершей еще\nв 1823 году, а памятник на могиле\nматери по проекту Монферрана был\nсооружен в 1830-х годах.\nУвлеченный неповторимой архи-\nтектурой нашего города, В. К. Шуй-\nский подготовил своеобразный\nпутеводитель по 30 дворцам города,\nопубликованный на русском и ан-\nглийском языках совсем недавно -\nв\n2006 году - «Императорские двор-\nцы Санкт-Петербурга». Это издание\nдает широкий и профессионально\nотработанный материал для экскур-\nсоводов и любителей архитектуры\nвторой столицы России.\nНеожиданный уход из жизни\nВ. К. Шуйского - невосполнимая\nпотеря длязанимающихсяизучени-\nем зарождения и развития архитек-\nтурногг облика Санкт-Петербурга,\nпоиском материалов по истории\nжизни идеятельности зодчих города\nна протяжении трех столетий его\nсуществования.\nB. К. Шуйский похоронен на\nКазанском кладбище г. Пушкина\nпосле отпевания в Софийском со-\nборе, историю созданиякоторого\nпередего реставрацией досконально\nизучил В. К. Шуйский, помогая\nправославной церкви.\nНаследие В. К. Шуйского - его\nмонография, статьи, научные раз-\nработки, богатый архив, память его\nродных, друзей и почитателей.\nПоследний\nопубликованный ма-\nтериал, подготовленный В. К. Шуй-\nским - его предисловие к четвер-\nтому изданию художественно-\nисторического романа И. А. Измай-\nловой «Собор», увидевшего свет в\n2007 году. Часть его работ осталась\nнезавершенной.\n99\nИстория Петербурга. №1 (47)/2009"
        }
    ]
}